README.txt
setup.cfg
setup.py
simplegeo/__init__.py
simplegeo/places/__init__.py
simplegeo/places/_version.py
simplegeo/places/test/__init__.py
simplegeo/places/test/test_client.py
simplegeo_places.egg-info/PKG-INFO
simplegeo_places.egg-info/SOURCES.txt
simplegeo_places.egg-info/dependency_links.txt
simplegeo_places.egg-info/namespace_packages.txt
simplegeo_places.egg-info/not-zip-safe
simplegeo_places.egg-info/requires.txt
simplegeo_places.egg-info/top_level.txt