Metadata-Version: 1.0
Name: simplegeo-places
Version: 2.4.153
Summary: Library for interfacing with SimpleGeo's Places API
Home-page: http://github.com/simplegeo/python-simplegeo-places
Author: Zooko Wilcox-O'Hearn
Author-email: zooko@simplegeo.com
License: MIT License
Keywords: simplegeo
Platform: UNKNOWN
